{
  "schema_version": 1,
  "updated_at": "2026-06-18",
  "predictions": [
    {
      "date_beijing": "2026-06-19",
      "time_beijing": "01:00",
      "home_team": "Czechia",
      "away_team": "South Africa",
      "group": "Group A",
      "venue": "Atlanta Stadium",
      "report": "reports/2026-06-19.html",
      "pick_1x2": "home",
      "primary_score": "1-0",
      "score_candidates": ["1-0", "1-1", "2-0", "2-1"],
      "confidence": 6,
      "notes": "阵容稳定性和定位球优势偏捷克，南非首战防线失误后预计更保守。"
    },
    {
      "date_beijing": "2026-06-19",
      "time_beijing": "04:00",
      "home_team": "Switzerland",
      "away_team": "Bosnia and Herzegovina",
      "group": "Group B",
      "venue": "Los Angeles Stadium",
      "report": "reports/2026-06-19.html",
      "pick_1x2": "home",
      "primary_score": "1-0",
      "score_candidates": ["1-0", "1-1", "2-0", "0-0"],
      "confidence": 6,
      "notes": "瑞士中后场质量和控球优势更明显，波黑低位防守使低比分概率较高。"
    },
    {
      "date_beijing": "2026-06-19",
      "time_beijing": "07:00",
      "home_team": "Canada",
      "away_team": "Qatar",
      "group": "Group B",
      "venue": "BC Place Vancouver",
      "report": "reports/2026-06-19.html",
      "pick_1x2": "home",
      "primary_score": "2-0",
      "score_candidates": ["2-0", "1-0", "2-1", "3-0"],
      "confidence": 7,
      "notes": "加拿大主场、速度和锋线深度占优，卡塔尔持续进攻质量不足。"
    },
    {
      "date_beijing": "2026-06-19",
      "time_beijing": "10:00",
      "home_team": "Mexico",
      "away_team": "Korea Republic",
      "group": "Group A",
      "venue": "Guadalajara Stadium",
      "report": "reports/2026-06-19.html",
      "pick_1x2": "draw",
      "primary_score": "1-1",
      "score_candidates": ["1-1", "2-1", "1-2", "2-2"],
      "confidence": 5,
      "notes": "墨西哥主场优势明显，但蒙特斯停赛给韩国反击和肋部穿插机会。"
    }
  ]
}
